projecteuler_cli/__init__.py
projecteuler_cli/cli.py
projecteuler_cli/fetch.py
projecteuler_cli/storage.py
projecteuler_cli-0.3.0.dist-info/METADATA
projecteuler_cli-0.3.0.dist-info/WHEEL
projecteuler_cli-0.3.0.dist-info/entry_points.txt
projecteuler_cli-0.3.0.dist-info/top_level.txt
projecteuler_cli-0.3.0.dist-info/RECORD
