Metadata-Version: 2.4
Name: projecteuler-cli
Version: 0.3.0
Summary: A tiny helper to fetch Project Euler problems, create boiler-plates, and track progress.
Author-email: Arnav Kalekar <akalekar@purdue.edu>
License: MIT
Requires-Python: >=3.9
Requires-Dist: requests
Requires-Dist: beautifulsoup4
